cbbs.cpython-38-darwin.so
cbbs-1.0.1.dist-info/RECORD
cbbs-1.0.1.dist-info/LICENSE
cbbs-1.0.1.dist-info/WHEEL
cbbs-1.0.1.dist-info/top_level.txt
cbbs-1.0.1.dist-info/METADATA
